space_explorer_mcp/__init__.py
space_explorer_mcp/server.py
space_explorer_mcp-0.1.0.dist-info/METADATA
space_explorer_mcp-0.1.0.dist-info/WHEEL
space_explorer_mcp-0.1.0.dist-info/entry_points.txt
space_explorer_mcp-0.1.0.dist-info/RECORD
