Metadata-Version: 2.4
Name: space-explorer-mcp
Version: 0.1.0
Summary: An awesome MCP server for exploring space! Track the ISS, get SpaceX launch data, discover NASA content, and learn fascinating space facts.
Requires-Python: >=3.10
Requires-Dist: fastmcp>=2.0.0
